liquidity/__init__.py
liquidity/compute/__init__.py
liquidity/compute/cache.py
liquidity/compute/ticker.py
liquidity/compute/utils/__init__.py
liquidity/compute/utils/dividends.py
liquidity/compute/utils/yields.py
liquidity/data/__init__.py
liquidity/data/config.py
liquidity/data/format.py
liquidity/data/metadata/__init__.py
liquidity/data/metadata/assets.py
liquidity/data/metadata/entities.py
liquidity/data/metadata/fields.py
liquidity/data/providers/__init__.py
liquidity/data/providers/alpaca_markets.py
liquidity/data/providers/alpha_vantage.py
liquidity/data/providers/base.py
liquidity/data/providers/fred.py
liquidity/exceptions.py
liquidity/models/__init__.py
liquidity/models/liquidity.py
liquidity/models/price_ratio.py
liquidity/models/yield_spread.py
liquidity/visuals/__init__.py
liquidity/visuals/chart.py
liquidity/visuals/matrix.py
liquidity-0.3.2.dist-info/LICENSE
liquidity-0.3.2.dist-info/METADATA
liquidity-0.3.2.dist-info/WHEEL
liquidity-0.3.2.dist-info/RECORD
