Metadata-Version: 2.3
Name: liquidity
Version: 0.3.2
Summary: Market liquidity proxies
License: MIT
Author: Marcin Dąmbski
Requires-Python: >=3.11,<4.0
Classifier: License :: OSI Approved :: MIT License
Classifier: Programming Language :: Python :: 3
Classifier: Programming Language :: Python :: 3.11
Classifier: Programming Language :: Python :: 3.12
Classifier: Programming Language :: Python :: 3.13
Requires-Dist: alpaca-py (>=0.35.0,<0.36.0)
Requires-Dist: alpha-vantage (>=3.0.0,<4.0.0)
Requires-Dist: fredapi (>=0.5.2,<0.6.0)
Requires-Dist: pandas (>=2,<3)
Requires-Dist: plotly (>=5.24.1,<6.0.0)
Requires-Dist: pydantic-settings (>=2.7.1,<3.0.0)
